route_planner/__init__.py
route_planner/google_routes_client.py
route_planner/schemas.py
traffic_aware_route_optimizer-1.0.0.dist-info/licenses/LICENSE
traffic_aware_route_optimizer-1.0.0.dist-info/METADATA
traffic_aware_route_optimizer-1.0.0.dist-info/WHEEL
traffic_aware_route_optimizer-1.0.0.dist-info/top_level.txt
traffic_aware_route_optimizer-1.0.0.dist-info/RECORD
