Metadata-Version: 2.4
Name: traffic-aware-route-optimizer
Version: 1.0.0
Summary: Traffic-aware route optimization using Google Routes API
Author: Luis Ticas
Author-email: Luis Ticas <luis.ticas1@gmail.com>
License-Expression: MIT
Project-URL: Homepage, https://github.com/lutic1/traffic-aware-route-optimizer
Project-URL: Repository, https://github.com/lutic1/traffic-aware-route-optimizer.git
Project-URL: Issues, https://github.com/lutic1/traffic-aware-route-optimizer/issues
Project-URL: Documentation, https://github.com/lutic1/traffic-aware-route-optimizer#readme
Keywords: route-optimization,google-routes,traffic-aware,logistics,navigation,gis
Classifier: Development Status :: 4 - Beta
Classifier: Intended Audience :: Developers
Classifier: Topic :: Scientific/Engineering :: GIS
Classifier: Topic :: Software Development :: Libraries :: Python Modules
Classifier: Programming Language :: Python :: 3
Classifier: Programming Language :: Python :: 3.8
Classifier: Programming Language :: Python :: 3.9
Classifier: Programming Language :: Python :: 3.10
Classifier: Programming Language :: Python :: 3.11
Classifier: Programming Language :: Python :: 3.12
Requires-Python: >=3.8
License-File: LICENSE
Requires-Dist: pydantic>=2.0.0
Requires-Dist: googlemaps>=4.10.0
Requires-Dist: httpx>=0.24.0
Dynamic: author
Dynamic: license-file
Dynamic: requires-python
